{
  "source": "japan_news",
  "fetched_at": "2026-03-05T19:08:39.064192+00:00",
  "total_fetched": 133,
  "unique_count": 133,
  "health_related_count": 51,
  "news": [
    {
      "id": "bb7e83ef868f",
      "title": "第23回日本臨床腫瘍学会の注目演題／JSMO2026｜医師向け医療ニュースはケアネット - CareNet.com",
      "published": "2026-03-05T19:00:00+00:00",
      "summary": "第23回日本臨床腫瘍学会の注目演題／JSMO2026｜医師向け医療ニュースはケアネット&nbsp;&nbsp;CareNet.com",
      "sources": [
        {
          "name": "CareNet.com",
          "link": "https://news.google.com/rss/articles/CBMiX0FVX3lxTE9mRDROYllxeFAzcXJqckFZNHhnVUVfa0lfUTBwOWVxRTJraTAtc0JoVVlhUEp3c0ttRWVFblBpM2FicFg5UVVKU2VDTGtGT3FDck9oQU5rTGN3WG5MNFY0?oc=5"
        }
      ]
    },
    {
      "id": "9b7a94136eb0",
      "title": "冠動脈疾患の画像診断、放射線被曝量に世界的格差／JAMA｜医師向け医療ニュースはケアネット - CareNet.com",
      "published": "2026-03-05T19:00:00+00:00",
      "summary": "冠動脈疾患の画像診断、放射線被曝量に世界的格差／JAMA｜医師向け医療ニュースはケアネット&nbsp;&nbsp;CareNet.com",
      "sources": [
        {
          "name": "CareNet.com",
          "link": "https://news.google.com/rss/articles/CBMiX0FVX3lxTE52elNqTk5sN1NGTzZxMkxCMmVvakhRbjR3QVZ5N1VlTWV3Z3VkaXRod2k1TVIwNDRxYVBkVmR3U2hoWmthSWUwNU9xS1ByLXpjak1sbnZxcjUtSm9FQUg0?oc=5"
        }
      ]
    },
    {
      "id": "443526e7cbbd",
      "title": "慢性片頭痛に対する抗CGRP抗体とCGRP受容体拮抗薬併用療法の有用性は？｜医師向け医療ニュースはケアネット - CareNet.com",
      "published": "2026-03-05T19:00:00+00:00",
      "summary": "慢性片頭痛に対する抗CGRP抗体とCGRP受容体拮抗薬併用療法の有用性は？｜医師向け医療ニュースはケアネット&nbsp;&nbsp;CareNet.com片頭痛、CGRP関連抗体薬治療で5割の患者で発作が半分以下に減少－慶大&nbsp;&nbsp;QLifeProどうすれば安全安心：片頭痛予防に抗体薬が有効&nbsp;&nbsp;毎日新聞",
      "sources": [
        {
          "name": "CareNet.com",
          "link": "https://news.google.com/rss/articles/CBMiX0FVX3lxTE9WX21oTkhJQzhyN3dvenhINEVDWEVSbnBDQ25CRnVsYXExbGxMeFBjb0lSbWY4dS1lWW5WaU5wYTNyTHNuNDcwUGNmYWVqcnB1NF9VU1B4cWE2VW9fd05j?oc=5"
        }
      ]
    },
    {
      "id": "0db1b101f307",
      "title": "スピアーズさん一時逮捕　運転時、既に釈放(共同通信)",
      "published": "2026-03-05T16:00:00+00:00",
      "summary": "【ロサンゼルス共同】米メディアは5日、西部カリフォルニア州の警察が、飲酒や薬物の影響下で運転した疑いで人気歌手ブリトニー・スピアーズさん（44）を4日に逮捕していたと報じた。既に釈放されたとしている",
      "sources": [
        {
          "name": "Yahoo! Japan Life",
          "link": "https://news.yahoo.co.jp/articles/a30af0d36086f48a26b4e7b71bcbea3fdabdfa1d?source=rss"
        }
      ]
    },
    {
      "id": "60165eddfab8",
      "title": "世界の富裕層が熱狂する「ぶっ飛んだ最新旅」が意味不明?! “冷凍療法”の隔離体験から、占星術で冒険を決める旅が話題(ウィメンズヘルス)",
      "published": "2026-03-05T14:00:02+00:00",
      "summary": "私は今、38℃の不思議な温泉に浸かっている。シーオイル、塩水、アロエ、ミントが注入されたその水は、肌に素晴らしい効果をもたらしてくれるという。イタリア・サルデーニャ島の「フォルテ・ヴィレッジ」にある7",
      "sources": [
        {
          "name": "Yahoo! Japan Life",
          "link": "https://news.yahoo.co.jp/articles/1b601648dc595f809d7f0ed6edbee9d2c3b095bf?source=rss"
        }
      ]
    },
    {
      "id": "abeda825293e",
      "title": "まだ花粉症でない人にも役立つ　体内への「花粉」の侵入、うまく軽減するコツとは(オトナンサー)",
      "published": "2026-03-05T13:15:00+00:00",
      "summary": "スギ花粉が本格的に飛散しており、鼻水やくしゃみなどの症状に悩まされている人は多いのではないでしょうか。花粉の体内への侵入を軽減する方法について、政府広報オンラインの公式Xアカウントが紹介しています。",
      "sources": [
        {
          "name": "Yahoo! Japan Life",
          "link": "https://news.yahoo.co.jp/articles/4a9bf5715f565bbcd4415ecc2c0974f73c62b39f?source=rss"
        }
      ]
    },
    {
      "id": "f4cbe63bb656",
      "title": "50歳で閉経、仕事が続けられないほどつらい「更年期症状」漢方という選択(Web eclat)",
      "published": "2026-03-05T13:10:01+00:00",
      "summary": "体調への不安から、仕事を辞めたあかりさん。不安感も強く、美容院の目の前まで来たのに入れなかったこともあったとか。100人いれば100通りと言われる更年期の不調。エクラ読者の皆さんの更年期体験を聞いてみ",
      "sources": [
        {
          "name": "Yahoo! Japan Life",
          "link": "https://news.yahoo.co.jp/articles/c24e83b0507ff517c951b8d1bc7840db2edb2a54?source=rss"
        }
      ]
    },
    {
      "id": "88635b89bfbd",
      "title": "「毎朝コップ1杯の美肌習慣」スーパーで買える「飲む美容液」(GISELe)",
      "published": "2026-03-05T12:52:00+00:00",
      "summary": "「甘酒は\"飲む点滴\"と呼ばれるほど体に良い」と聞くけれど、「本当に美容や肌にいいの？」「どう飲めば効果的なの？」と気になっていませんか？ 結論から言うと、米糀（こめこうじ）から作られた甘酒は、美容と健",
      "sources": [
        {
          "name": "Yahoo! Japan Life",
          "link": "https://news.yahoo.co.jp/articles/1c5e4eb441d4dfbf5c5acef903e87e2ef461a141?source=rss"
        }
      ]
    },
    {
      "id": "314de3b6fc93",
      "title": "Q.マイナ保険証の代わりになる「資格確認書」っていつまで使い続けられるんですか？(All About)",
      "published": "2026-03-05T12:50:01+00:00",
      "summary": "2024年12月2日から従来の健康保険証の新規発行が停止され、2025年12月2日からは原則利用不可になりました。医療機関の受診は「マイナ保険証（マイナンバーカード）」を基本とすることになり、マイナ保",
      "sources": [
        {
          "name": "Yahoo! Japan Life",
          "link": "https://news.yahoo.co.jp/articles/b6a757a69d5fa0abf4deae539f06ebecc5cc1389?source=rss"
        }
      ]
    },
    {
      "id": "a4ac071130c9",
      "title": "ADHDの3つのタイプを特定、脳の特徴と症状の表れ方とは - ナショナルジオグラフィック日本版",
      "published": "2026-03-05T12:00:00+00:00",
      "summary": "ADHDの3つのタイプを特定、脳の特徴と症状の表れ方とは&nbsp;&nbsp;ナショナルジオグラフィック日本版",
      "sources": [
        {
          "name": "ナショナルジオグラフィック日本版",
          "link": "https://news.google.com/rss/articles/CBMicEFVX3lxTE94SFUtbFF0R0RlY0pCMVl2RnFOUmJZUFIxRmdka1RmUXF2Y0N1eEtxMWMxWnBnV2lNc1FrcWRsLU1fYUYtV2RYSjhBajZBMnhhWDZvNU1fMmNHM1V6Zks0TmlhckRZbllnWl9IWjdBLVk?oc=5"
        }
      ]
    },
    {
      "id": "28150d64def6",
      "title": "〈目撃〉100平方m超、11万匹の巨大なクモの巣ほか奇妙すぎる巣を続々発見(ナショナル ジオグラフィック日本版)",
      "published": "2026-03-05T11:11:37+00:00",
      "summary": "アルバニアとギリシャの国境にある地下洞窟の狭い通路で、科学者たちは濁った水に腰まで漬かり、ロープにしがみ付きながら驚くべき発見をした。懐中電灯の光のなかに、きらめくクモの巣の壁が広がっていたのだ。こ",
      "sources": [
        {
          "name": "Yahoo! Japan Science",
          "link": "https://news.yahoo.co.jp/articles/784214cf706e8446ffc2ca030d1df59694717e56?source=rss"
        }
      ]
    },
    {
      "id": "0817472c5495",
      "title": "愛知県で新たに2人はしか感染 感染経路不明の患者も 今年確認の県内感染者数は23人に - au Webポータル",
      "published": "2026-03-05T11:10:00+00:00",
      "summary": "愛知県で新たに2人はしか感染 感染経路不明の患者も 今年確認の県内感染者数は23人に&nbsp;&nbsp;au Webポータル愛知県で新たに2人はしか感染 感染経路不明の患者も 今年確認の県内感染者数は23人に（メ〜テレ（名古屋テレビ））&nbsp;&nbsp;Yahoo!ニュースはしか発症 内装業者も 感染相次ぐ愛知県立高校に出入り&nbsp;&nbsp;nagoyatv.com発症前日の2/23にドラッグストア訪れる…岐阜市に住む40代男性“はしか”の感染を確認 岐阜県内では今年初めて&nbsp;&nbsp;東海テレビ放送岐阜市の４０代男性、はしかに感染&nbsp;&nbsp;岐阜新聞デジタル",
      "sources": [
        {
          "name": "au Webポータル",
          "link": "https://news.google.com/rss/articles/CBMie0FVX3lxTE1EZ0NTUUxhRWFOR1ZoZTJTMUItaTE5UGZaNUhneFRRamRXRjhEMk9PUmJlTEhfcV9XYmhaQ0xGQXM0VlRicG9YV19FTXFBeWwzSHV1ZDFnMGNocDNCX3JxWmpkYnJ0T2kxNnEzb0dEQmRDXzN6ZVVNYWhZSQ?oc=5"
        }
      ]
    },
    {
      "id": "f10c847cf48f",
      "title": "「美容院脳卒中症候群」の症状やなりやすい人の特徴はご存知ですか？【医師解説】(メディカルドック)",
      "published": "2026-03-05T11:04:53+00:00",
      "summary": "美容院脳卒中症候群とは？メディカルドック監修医が美容院脳卒中症候群の症状・原因・なりやすい人の特徴・後遺症・治療法・予防法や何科へ受診すべきかなどを解説します。気になる症状がある場合は迷わず病院を受診",
      "sources": [
        {
          "name": "Yahoo! Japan Science",
          "link": "https://news.yahoo.co.jp/articles/8f8707880bff863b3bd1fbdaefdb953150fe69fe?source=rss"
        }
      ]
    },
    {
      "id": "03175ee2b3cb",
      "title": "【訃報】俳優・勝呂誉さん 「肺がん」の症状や“痛みが現れる場所”を医師が解説(メディカルドック)",
      "published": "2026-03-05T10:26:14+00:00",
      "summary": "俳優の勝呂誉（すぐろ・ほまれ）さんが1月23日に、肺がんのため亡くなっていたことを所属の芸能事務所が公表しました。85歳でした。 ここでは、予防の観点から、肺がんで痛みが現れる場所や原因・症状などに",
      "sources": [
        {
          "name": "Yahoo! Japan Science",
          "link": "https://news.yahoo.co.jp/articles/f6900eab2e652a70d4128ed06099e579a0827a65?source=rss"
        }
      ]
    },
    {
      "id": "59f902eb5e15",
      "title": "カイロス3号機、ロケット開発の「魔物」に勝てず　失敗に学び経験値アップで次回は成功を(産経新聞)",
      "published": "2026-03-05T10:05:28+00:00",
      "summary": "「ロケット開発は、どこにいるか分からない魔物に立ち向かうようなものだ」。宇宙系の技術者はよく、こんなことを言う。使用環境が過酷で、何が起きるか想定しづらいからだ。打ち上げに失敗した宇宙事業会社スペース",
      "sources": [
        {
          "name": "Yahoo! Japan Science",
          "link": "https://news.yahoo.co.jp/articles/03be14ae99bd8721506314e98528b5981adde27c?source=rss"
        }
      ]
    },
    {
      "id": "929295a986cc",
      "title": "「徹夜は効果なし」睡眠研究者が解説　記憶の固定には学習した日に6時間以上眠ることが不可欠(AERA DIGITAL)",
      "published": "2026-03-05T08:00:36+00:00",
      "summary": "睡眠中に記憶の固定、強化が行われていると言われ、眠ることが記憶に大きく関係しています。名古屋市立大学教授の粂和彦氏による新刊、朝日選書『脳がないのにクラゲも眠る 生物に宿された「睡眠」の謎に迫る』（",
      "sources": [
        {
          "name": "Yahoo! Japan Science",
          "link": "https://news.yahoo.co.jp/articles/1204c2ec780dd5ffe053ed7cf6394f68fc86f575?source=rss"
        }
      ]
    },
    {
      "id": "e9330155a13c",
      "title": "【速報】カイロス3号機「失敗ということとは考えていない」　スペースワン社長が会見で言明　5日の打ち上げは「飛行中断措置」でミッション達成ならず(MBSニュース)",
      "published": "2026-03-05T06:35:21+00:00",
      "summary": "和歌山県で打ち上げを目指している民間ロケット「カイロス」の3号機。きょう5日に発射されましたが、「飛行中断措置」によりミッション達成には至りませんでした。今回の打ち上げについて、開発したスペースワン",
      "sources": [
        {
          "name": "Yahoo! Japan Science",
          "link": "https://news.yahoo.co.jp/articles/42f662d07f5ceb3f2647fda27591a38e093d8e2a?source=rss"
        }
      ]
    },
    {
      "id": "d0b4b21e1f41",
      "title": "【速報】民間ロケット・カイロス　4号機の打ち上げは「いつとは申し上げにくい」　3号機「飛行中断措置」の原因究明に時間をかけて取り組む考え　スペースワン社が説明(MBSニュース)",
      "published": "2026-03-05T06:19:36+00:00",
      "summary": "和歌山県で打ち上げを目指している民間ロケット「カイロス」の3号機。きょう5日に発射されましたが、「飛行中断措置」によりミッション達成には至りませんでした。今回の打ち上げについて開発したスペースワンが",
      "sources": [
        {
          "name": "Yahoo! Japan Science",
          "link": "https://news.yahoo.co.jp/articles/5fdee0de80247c0095921ca08793b44a453e8c6c?source=rss"
        }
      ]
    },
    {
      "id": "9bc2e4852a2d",
      "title": "【速報】「環境に問題なし」「機体・機器に異常認められず」もカイロス3号機はリフトオフから68.8秒後に「飛行中断措置」1段目のモーターが燃焼中　ミッション達成ならず…スペースワン社が会見で説明(MBSニュース)",
      "published": "2026-03-05T06:14:48+00:00",
      "summary": "和歌山県で打ち上げを目指している民間ロケット「カイロス」の3号機。きょう5日に発射されましたが、「飛行中断措置」によりミッション達成には至りませんでした。今回の打ち上げについて開発したスペースワンが",
      "sources": [
        {
          "name": "Yahoo! Japan Science",
          "link": "https://news.yahoo.co.jp/articles/17706ccb311bd6312228869ad24e248d71d4caaa?source=rss"
        }
      ]
    },
    {
      "id": "547e1a2c8fbf",
      "title": "【速報】「自立飛行安全システムが作動し飛行中断」カイロス3号機「飛行中断措置」でミッション達成ならず　開発したスペースワン社が会見で説明(MBSニュース)",
      "published": "2026-03-05T06:06:02+00:00",
      "summary": "和歌山県で打ち上げを目指している民間ロケット「カイロス」の3号機。きょう5日に発射されましたが、「飛行中断措置」によりミッション達成には至りませんでした。今回の打ち上げについて開発したスペースワンが",
      "sources": [
        {
          "name": "Yahoo! Japan Science",
          "link": "https://news.yahoo.co.jp/articles/cb1ac290cbcd99a0360ea2d406ef5f5753ee97a7?source=rss"
        }
      ]
    },
    {
      "id": "79d47e0507c3",
      "title": "下痢が1か月以上続いたら要注意――炎症性腸疾患「IBD」とは(Medical Note)",
      "published": "2026-03-05T04:51:35+00:00",
      "summary": "「週に5日はお腹が痛くなる」、「よく下痢に悩まされている」。そんな症状があっても、体質のせいやストレスのせいと軽く考えて、医療機関には行かず様子を見ているという人は少なくないのではないか。しかし、そこ",
      "sources": [
        {
          "name": "Yahoo! Japan Science",
          "link": "https://news.yahoo.co.jp/articles/7a018a8fe190ac32d956be7d8392d807010b3045?source=rss"
        }
      ]
    },
    {
      "id": "abb944ca94bd",
      "title": "D型インフルエンザウイルスの高度ゲノム再構築法―基礎・応用研究をつなぐ新技術 - a.u-tokyo.ac.jp",
      "published": "2026-03-05T04:31:57+00:00",
      "summary": "D型インフルエンザウイルスの高度ゲノム再構築法―基礎・応用研究をつなぐ新技術&nbsp;&nbsp;a.u-tokyo.ac.jp",
      "sources": [
        {
          "name": "a.u-tokyo.ac.jp",
          "link": "https://news.google.com/rss/articles/CBMiaEFVX3lxTE9CdlRqOXFZZmpPQVMzZS1MbTZtalRPRGtKYmcwc3g2MEVfLU9jcC1Wb0EwbFR4cUlXaUlMYVZqLUswb1RZU19ObDFFa1VPamdCZzFVcEpvNF9taXBVelozWWM5Mk5OMUNu?oc=5"
        }
      ]
    },
    {
      "id": "3ef07f420b56",
      "title": "【ヤフコメで話題】「カイロス3号機の連続失敗に厳しい声」「民間小型ロケット開発の難しさと今後への期待」 - カイロス3号機打ち上げ失敗を巡る議論(Yahoo!ニュース オリジナル THE PAGE)",
      "published": "2026-03-05T04:23:23+00:00",
      "summary": "カイロス3号機の打ち上げ失敗について、Yahoo!ニュースのコメント欄で話題になっています。 コメントでは、同じ固体燃料を使ったイプシロンロケット6号機の失敗と類似点を指摘する声や、打ち上げ直後からの",
      "sources": [
        {
          "name": "Yahoo! Japan Science",
          "link": "https://news.yahoo.co.jp/articles/d18caf18d6b023d1edf830afbf68da0c8e7aa491?source=rss"
        }
      ]
    },
    {
      "id": "b78788b524e7",
      "title": "鼻からスプレーするだけでウイルス・細菌・アレルギーに効く万能ワクチンが開発中 - ライブドアニュース",
      "published": "2026-03-05T04:01:00+00:00",
      "summary": "鼻からスプレーするだけでウイルス・細菌・アレルギーに効く万能ワクチンが開発中&nbsp;&nbsp;ライブドアニュース",
      "sources": [
        {
          "name": "ライブドアニュース",
          "link": "https://news.google.com/rss/articles/CBMiX0FVX3lxTE5fd0VSdU5MTm9NbkZVbkZnRDVHemlZTE9lUlZhR2pKZFRzMnRiQVZfSGdqeVZ2UVFVVVFoY0Njbk1vMV9zdE8tYlRvdDc3RXZxUWpIeU5zcndnNHExNnJF?oc=5"
        }
      ]
    },
    {
      "id": "66c9d680a35f",
      "title": "元参議院議員の大塚耕平さん「心不全」で死去。前兆となる初期症状・末期症状を医師が解説！(メディカルドック)",
      "published": "2026-03-05T02:17:03+00:00",
      "summary": "元参議院議員でおととし名古屋市長選にも出馬した大塚耕平さんが、「心不全」で亡くなったと報じられています。66歳でした。そこで、心不全の前兆となる初期症状・末期症状について医師の伊藤先生に解説してもらい",
      "sources": [
        {
          "name": "Yahoo! Japan Science",
          "link": "https://news.yahoo.co.jp/articles/a91baf63e2600943b472d76e1c16e23959866edb?source=rss"
        }
      ]
    },
    {
      "id": "02714f24c0bd",
      "title": "ベージュ細胞を誘導する食餌と腸内細菌を同定 - riken.jp",
      "published": "2026-03-05T02:12:56+00:00",
      "summary": "ベージュ細胞を誘導する食餌と腸内細菌を同定&nbsp;&nbsp;riken.jp",
      "sources": [
        {
          "name": "riken.jp",
          "link": "https://news.google.com/rss/articles/CBMiY0FVX3lxTE1ZdUVvVzBjNk4tYThyTjN0by0tS093U1ZOdHJ4OTl2cGlfUWJJTFVZYWJrUWp5SVU1WFFmVU8yRUxIZzZzLVNhYnVSek1TX1pRLUs4ZEhMVFRQLUsyMC1MbmNWMA?oc=5"
        }
      ]
    },
    {
      "id": "bd083d010023",
      "title": "帯状疱疹のワクチン、２０２７～２９年度の定期接種対象者が２６年度に接種しても補助…中間市と４町 - 読売新聞オンライン",
      "published": "2026-03-05T01:36:00+00:00",
      "summary": "帯状疱疹のワクチン、２０２７～２９年度の定期接種対象者が２６年度に接種しても補助…中間市と４町&nbsp;&nbsp;読売新聞オンライン帯状疱疹、発症しやすくなる要因は加齢やストレス ワクチンについて医師が解説（西日本新聞）&nbsp;&nbsp;Yahoo!ニュース帯状疱疹ワクチンが認知症を防ぐ？最新の大規模研究が明かす驚きの研究結果&nbsp;&nbsp;newspicks.com帯状疱疹ワクチンが認知症を予防？ 相次ぐ研究結果が示す可能性&nbsp;&nbsp;WIRED.jp帯状疱疹のワクチン、２０２７～２９年度の定期接種対象者が２６年度に接種しても補助…中間市と４町（読売新聞オンライン）&nbsp;&nbsp;Yahoo!ニュース",
      "sources": [
        {
          "name": "読売新聞オンライン",
          "link": "https://news.google.com/rss/articles/CBMickFVX3lxTE4zamNEZWw1Q1dfeHh0TThxMmtKWW5FOTZ4VDZWNHFRX2s1TUZ1elBVcXFsUTN5cGFRY0xCRWxKZWQ0bFE0c1ZaOE16REpaOXJEX25qaGJxSDNyY1h3U1VfSzdmTVRXcFFUZnhsejV1SnZSQQ?oc=5"
        }
      ]
    },
    {
      "id": "308a1d42c9dc",
      "title": "ヒトの遺伝子の2割は150万年前の「幻の人類」に由来する(Forbes JAPAN)",
      "published": "2026-03-05T01:30:00+00:00",
      "summary": "進化をめぐる優勢な説では、何十年ものあいだ、ホモ・サピエンスはおよそ20～30万年前にアフリカで出現したが、すべてが単一の祖先集団に由来するとされてきた。この仮説は、「アフリカ単一起源説」として知られ",
      "sources": [
        {
          "name": "Yahoo! Japan Science",
          "link": "https://news.yahoo.co.jp/articles/6f81a0e9841dbcc08294c86434c3c29ccaad51c5?source=rss"
        }
      ]
    },
    {
      "id": "930a94436793",
      "title": "マツキヨココカラが女性の健康支援で新施策―「女性活躍」の壁 克服目指す(メディカルドック)",
      "published": "2026-03-05T01:01:18+00:00",
      "summary": "全国に約3600店舗を展開するドラッグストアグループ、株式会社マツキヨココカラ&カンパニー（以下「マツキヨココカラ」）は大塚製薬株式会社と連携し、女性の健康と働きやすさを支える新たな取り組みを2026",
      "sources": [
        {
          "name": "Yahoo! Japan Science",
          "link": "https://news.yahoo.co.jp/articles/d78c6a244952a7e6ca0bc8443185176962a281c7?source=rss"
        }
      ]
    },
    {
      "id": "e134e90474ec",
      "title": "鳥インフルエンザが乳牛に感染した原因は何か？米国で広がる酪農経済への打撃、私たちはどう対応すべきか - ｄメニューニュース",
      "published": "2026-03-05T00:00:00+00:00",
      "summary": "鳥インフルエンザが乳牛に感染した原因は何か？米国で広がる酪農経済への打撃、私たちはどう対応すべきか&nbsp;&nbsp;ｄメニューニュースGoogle ニュースですべての記事を見る",
      "sources": [
        {
          "name": "ｄメニューニュース",
          "link": "https://news.google.com/rss/articles/CBMicEFVX3lxTE9yQklySTNRclBBUkJud2N5ZGJmZk8zR2ZlNEVHQURFWXRsYmVGbVBMeW5DbE9FaVBMWGlZTU42cENHTmQ5WGZFYmlsV2VMQ2NSX2x2akVrdGw0eFBzcXNIZWtqbEhzQmJBWDdfako4NEU?oc=5"
        }
      ]
    },
    {
      "id": "5f51f0432717",
      "title": "心臓発作の転帰における「性別とフレイルのパラドックス」 - m3.com",
      "published": "2026-03-04T21:03:25+00:00",
      "summary": "心臓発作の転帰における「性別とフレイルのパラドックス」&nbsp;&nbsp;m3.com",
      "sources": [
        {
          "name": "m3.com",
          "link": "https://news.google.com/rss/articles/CBMiUkFVX3lxTE5sMTVsME00Y3N3V0JWa3g4QmM3VXZveDhjdTh5VGJVUXNTS1dwM0g3UkNMZl8wOGF5dG93WWZaNzRWN1JyTC00WThYRUI3Rnp4N1E?oc=5"
        }
      ]
    },
    {
      "id": "ff8b1ce7f3bb",
      "title": "高リスク上咽頭がん、camrelizumabの上乗せ・維持療法が有効／BMJ｜CareNet.com - CareNet.com",
      "published": "2026-03-04T19:00:00+00:00",
      "summary": "高リスク上咽頭がん、camrelizumabの上乗せ・維持療法が有効／BMJ｜CareNet.com&nbsp;&nbsp;CareNet.com",
      "sources": [
        {
          "name": "CareNet.com",
          "link": "https://news.google.com/rss/articles/CBMiX0FVX3lxTE9zeFZWZ2NwLTNzRXByOWljNERWTE1CY2phMzV0WFFLWmNpZFZGdjZrdnY4TGFoU2ZueEFkcTA3SjdxZTFNZVNSR0ZBQ2JOUUMwZUhrR0YzNEtiZGhxb2Zr?oc=5"
        }
      ]
    },
    {
      "id": "42336a1ebd09",
      "title": "市中肺炎への抗菌薬、72時間以内の経口剤への切り替えは安全？｜医師向け医療ニュースはケアネット - CareNet.com",
      "published": "2026-03-04T19:00:00+00:00",
      "summary": "市中肺炎への抗菌薬、72時間以内の経口剤への切り替えは安全？｜医師向け医療ニュースはケアネット&nbsp;&nbsp;CareNet.com",
      "sources": [
        {
          "name": "CareNet.com",
          "link": "https://news.google.com/rss/articles/CBMiX0FVX3lxTFBJa0p5MmQxaHJGa3lUTWhQZmcyQnd5TXNJVDczYkdiQjd2c1duZThhQmI0Y2JwZmNhbmUzNmRRMjhpZ3BsLUxHUEJMNUdXR3AtSzY3SlRfR3UyRmVWc3dB?oc=5"
        }
      ]
    },
    {
      "id": "2d1a5fdb111b",
      "title": "持効性注射剤ART、HIV患者の服薬アドヒアランス向上に寄与／NEJM｜CareNet.com - CareNet.com",
      "published": "2026-03-04T19:00:00+00:00",
      "summary": "持効性注射剤ART、HIV患者の服薬アドヒアランス向上に寄与／NEJM｜CareNet.com&nbsp;&nbsp;CareNet.com",
      "sources": [
        {
          "name": "CareNet.com",
          "link": "https://news.google.com/rss/articles/CBMiX0FVX3lxTE9ablYwbFl0dEVlejFEaGZOblp0U1E5eEQtdE1YLXkyMWFBa3VVZnFoQ1ZSSUk5RGRMWVgxcVZpLUNkUlh5bk9TbFU1TXM3cUNmT1BzcDRJQVo2VWNicll3?oc=5"
        }
      ]
    },
    {
      "id": "0cd5a506ba68",
      "title": "バンコク北郊タマサート大学ランシット校で「水痘」集団感染 疾病管理局が緊急調査 - newsclip.be",
      "published": "2026-03-04T17:10:14+00:00",
      "summary": "バンコク北郊タマサート大学ランシット校で「水痘」集団感染 疾病管理局が緊急調査&nbsp;&nbsp;newsclip.be",
      "sources": [
        {
          "name": "newsclip.be",
          "link": "https://news.google.com/rss/articles/CBMiWkFVX3lxTFBBYmFFOXJBSjBtcFh0REM4TUh3Wklha3B5Y2xJbms3OWRPSFE3WW1WMmJYRGJISUg2T1VLaHJETjMyYk5xUW45emdBWGlSYmdTUzY1SzJCMFQydw?oc=5"
        }
      ]
    },
    {
      "id": "23e67d72c71b",
      "title": "お酒を飲むと『糖尿病』になりやすい？ 原因や初期症状を専門医が詳しく解説 - メディカルドック",
      "published": "2026-03-04T13:02:24+00:00",
      "summary": "お酒を飲むと『糖尿病』になりやすい？ 原因や初期症状を専門医が詳しく解説&nbsp;&nbsp;メディカルドック",
      "sources": [
        {
          "name": "メディカルドック",
          "link": "https://news.google.com/rss/articles/CBMiWEFVX3lxTFBzcTR1cjM1dHozWF9xY3htRzlDdmJVZEtzalNJM2hQZktxSVhMaU9BZWxRUG43REhSTGtQMklkOFAyVTFBSkVBdmJ2SlA4TEFNMEl2SVZBalA?oc=5"
        }
      ]
    },
    {
      "id": "119e29bf8240",
      "title": "〈目撃〉ヘビのように踊る新種のカマキリを発見、独特な求愛ダンスで共食い回避か(ナショナル ジオグラフィック日本版)",
      "published": "2026-03-04T11:10:34+00:00",
      "summary": "カマキリのメスは、交尾中や交尾後にオスを食べることで悪名高い。しかし、オスが精巧なダンスを披露し、その運命を回避する小型のカマキリ「ドワーフ・マンティス」の新種を科学者たちが発見し、2025年11月",
      "sources": [
        {
          "name": "Yahoo! Japan Science",
          "link": "https://news.yahoo.co.jp/articles/a1e02dc6d5d34d92ce5eef857bb68dde6bfd08b7?source=rss"
        }
      ]
    },
    {
      "id": "0a689316b05a",
      "title": "「片頭痛は遺伝する」は本当なのか？ 発症を防ぐための生活習慣を医師が解説(メディカルドック)",
      "published": "2026-03-04T11:03:37+00:00",
      "summary": "片頭痛は、日本人の約840万人が抱えているとされ、特に30〜40代の女性に多い疾患です。頭痛が起こると仕事や家事が手につかない方も多いのではないでしょうか？ 近年は新しい治療薬の選択肢も増え、医療",
      "sources": [
        {
          "name": "Yahoo! Japan Science",
          "link": "https://news.yahoo.co.jp/articles/7201fddb91820ead03b0aefe18b3d0db62a9dfca?source=rss"
        }
      ]
    },
    {
      "id": "2aaf3d4bbf49",
      "title": "陰茎がん、尖圭コンジローマも関連…男子がHPVワクチン接種を検討する意義 (2026年3月4日掲載) - ライブドアニュース",
      "published": "2026-03-04T10:51:16+00:00",
      "summary": "陰茎がん、尖圭コンジローマも関連…男子がHPVワクチン接種を検討する意義 (2026年3月4日掲載)&nbsp;&nbsp;ライブドアニュース男子校で性教育を伝える産婦人科医が答える、男子にHPVワクチンが必要な理由と子どもたちへの伝え方（FRaU）&nbsp;&nbsp;Yahoo!ニュースHPVワクチンの男性への定期接種は実現するか？先行する豪では子宮頸がん撲滅も見えてきた&nbsp;&nbsp;ダイヤモンド・オンライン男性の罹患率が高い中咽頭がんは増加傾向に…。男子HPVワクチン接種が世界で広がるこれだけの理由&nbsp;&nbsp;現代ビジネス＜あぶない！＞HPVは女性だけの問題じゃない 男性もワクチン接種を&nbsp;&nbsp;中日新聞Web",
      "sources": [
        {
          "name": "ライブドアニュース",
          "link": "https://news.google.com/rss/articles/CBMiXkFVX3lxTE9pbVhBUEZQbDZpa0ZUUGthTWJkMUtxWGd1aW1tTnNjYlFGUFVkMzNHZUMtNUR6bzByZUVzSWhENFV1dkF2UVkwUW1JaW84UjMyTzBwSVBZODBYeVE3TFE?oc=5"
        }
      ]
    },
    {
      "id": "cfdd95a547a3",
      "title": "太古の交雑、組み合わせは「ネアンデルタール人の男性」と「現生人類の女性」か　米研究(CNN.co.jp)",
      "published": "2026-03-04T08:37:00+00:00",
      "summary": "（CNN） 初期の現生人類（ホモ・サピエンス）と、約4万年前に絶滅した旧人のネアンデルタール人が交雑していたとの研究結果は2010年に発表され、古人類学界に衝撃を与えた。 この太古の交雑について、米",
      "sources": [
        {
          "name": "Yahoo! Japan Science",
          "link": "https://news.yahoo.co.jp/articles/ec359e40d877d11141d14047a0fa0a7fc7299736?source=rss"
        }
      ]
    },
    {
      "id": "d0828173cafc",
      "title": "｢良かれと思って｣で最悪の場合死に至る…薬剤師｢インフル疑いの子供に飲ませてはいけない｣\"市販薬の名前\" - ライブドアニュース",
      "published": "2026-03-04T08:15:00+00:00",
      "summary": "｢良かれと思って｣で最悪の場合死に至る…薬剤師｢インフル疑いの子供に飲ませてはいけない｣\"市販薬の名前\"&nbsp;&nbsp;ライブドアニュース",
      "sources": [
        {
          "name": "ライブドアニュース",
          "link": "https://news.google.com/rss/articles/CBMiX0FVX3lxTE1SdGUwOGQzNW90bldKamg5d3ltY1BKZ2RKR2VSTXlEMVp0MzhRRVhHTVZSa3Nlamdpa2U1NUdMWl9mdjB0MlNMek1LYzN1MlFNRUxUaEJtMEgzSzAxMGFB?oc=5"
        }
      ]
    },
    {
      "id": "28afe7ac11ec",
      "title": "【人生100年社会 支える科学】第2回 免疫の司令塔を動かす乳酸菌が体を守る キリン・ヘルスサイエンス研究所長 村島弘一郎さん(Science Portal)",
      "published": "2026-03-04T08:03:56+00:00",
      "summary": "キリングループは長年培った発酵・バイオテクノロジーを武器に、未病領域で革新的な挑戦を続けている。免疫の司令塔である「樹状細胞」を直接活性化し、ウイルス感染防御の司令塔を動かす「プラズマ乳酸菌」や、最",
      "sources": [
        {
          "name": "Yahoo! Japan Science",
          "link": "https://news.yahoo.co.jp/articles/9ff4fa36cb7868ca4b1cfc6baea18058d8572311?source=rss"
        }
      ]
    },
    {
      "id": "b1706669a1a9",
      "title": "オリーブオイルと運動で糖代謝を促進 肥満予防に新たな示唆 J-オイルミルズと2大学が共同研究 - 食品新聞 WEB版",
      "published": "2026-03-04T05:54:52+00:00",
      "summary": "オリーブオイルと運動で糖代謝を促進 肥満予防に新たな示唆 J-オイルミルズと2大学が共同研究&nbsp;&nbsp;食品新聞 WEB版",
      "sources": [
        {
          "name": "食品新聞 WEB版",
          "link": "https://news.google.com/rss/articles/CBMiYEFVX3lxTE5INWYxNHlZTlJTV2x6eUlDN0IyWktiMlFaSjNmQll5UmIwNlZHTkVQM2ZEbXBDNk1sQVhlSFpsbFpTa1RSTmRMNTRSOUpsNXc4T1ZHajBEYllTSW9ncmRqQQ?oc=5"
        }
      ]
    },
    {
      "id": "20c4b6d8a540",
      "title": "低濃度麻酔薬での無痛分娩、赤ちゃんの安全性再確認 成育医療センター - 医療介護CBnews",
      "published": "2026-03-04T05:45:00+00:00",
      "summary": "低濃度麻酔薬での無痛分娩、赤ちゃんの安全性再確認 成育医療センター&nbsp;&nbsp;医療介護CBnews",
      "sources": [
        {
          "name": "医療介護CBnews",
          "link": "https://news.google.com/rss/articles/CBMiW0FVX3lxTE8wbEVQOXlGeE1OdkdxTm9Xd0dBblR1b0FtSWJQdXJ6Vkk2VDNrRkg3OXB1RkJBTUVfU3VOazJHdVo0V3lxa0E1VUN6VGxPTHQxMjNKQ2djeFVtT0E?oc=5"
        }
      ]
    },
    {
      "id": "81d603b4d890",
      "title": "「緩徐進行1型糖尿病」へのメトグルコ・ジャヌビアなど、「妊娠糖尿病」へのトレシーバ・ランタス、保険診療内で使用可能 社会保険診療報酬支払基金 - 糖尿病リソースガイド",
      "published": "2026-03-04T02:53:00+00:00",
      "summary": "「緩徐進行1型糖尿病」へのメトグルコ・ジャヌビアなど、「妊娠糖尿病」へのトレシーバ・ランタス、保険診療内で使用可能 社会保険診療報酬支払基金&nbsp;&nbsp;糖尿病リソースガイド",
      "sources": [
        {
          "name": "糖尿病リソースガイド",
          "link": "https://news.google.com/rss/articles/CBMia0FVX3lxTE41TDRqQk5LTW5Wall6OGQ2aDFwSm5OZGpMRjZNOGtRRlZseHlXTnhsUmJ6ZXh6V3d1TlJSR3NZYmVpNE5iWllOQmcxWXFNTnZ6TWVxb2R1SUxVNldUXy1WbWduT1VWSDcwQ3JN?oc=5"
        }
      ]
    },
    {
      "id": "9f3a7a6e74c9",
      "title": "肥満はアルツハイマー病の発症リスクではない可能性～脳内の脂質変動に遺伝子以外の制御が関与することを示唆～ - Digital PR Platform",
      "published": "2026-03-04T02:23:58+00:00",
      "summary": "肥満はアルツハイマー病の発症リスクではない可能性～脳内の脂質変動に遺伝子以外の制御が関与することを示唆～&nbsp;&nbsp;Digital PR Platform",
      "sources": [
        {
          "name": "Digital PR Platform",
          "link": "https://news.google.com/rss/articles/CBMiQ0FVX3lxTFBhQlVBV3pxVjJ1NHlUWkxmaU1fNm1ST1hIRHMzSTVQY0JzWjk0M25mb0hMOU9PaWFqWGg4M09LWWg3QkU?oc=5"
        }
      ]
    },
    {
      "id": "3821eed4b0f6",
      "title": "健康成人における急性単純性虫垂炎に対する治療戦略の選択肢：APPAC 10年追跡（解説：寺田 教彦 氏）－2089 - CareNet.com",
      "published": "2026-03-04T01:00:10+00:00",
      "summary": "健康成人における急性単純性虫垂炎に対する治療戦略の選択肢：APPAC 10年追跡（解説：寺田 教彦 氏）－2089&nbsp;&nbsp;CareNet.com",
      "sources": [
        {
          "name": "CareNet.com",
          "link": "https://news.google.com/rss/articles/CBMiXEFVX3lxTFB6a0p1UmNhUWItTmJRNmJVN1VKVnBvdElBcV9PYXNNQllDeEppM0RLdWgxTFhHdzhsb1dSalcwbFN5dFBnSkZJb0tmcnk1NktsV2lWVy1zUGhWWFFr?oc=5"
        }
      ]
    },
    {
      "id": "28fe40a091e1",
      "title": "80歳を過ぎても脳は育つ？スーパーエイジャーの記憶力を支える『再生力』 - WirelessWire",
      "published": "2026-03-03T21:02:05+00:00",
      "summary": "80歳を過ぎても脳は育つ？スーパーエイジャーの記憶力を支える『再生力』&nbsp;&nbsp;WirelessWire年をとっても記憶力が優れている「スーパーエイジャー」の脳に見られる特徴とは？&nbsp;&nbsp;GIGAZINE80歳を過ぎても脳は育つ？スーパーエイジャーの記憶力を支える『再生力』（WirelessWire News）&nbsp;&nbsp;ｄメニューニュース【鎌田實氏寄稿】人との関わりを大切に スーパーエイジャーを目指そう:人生100年時代の新健康法&nbsp;&nbsp;福島民友新聞社",
      "sources": [
        {
          "name": "WirelessWire",
          "link": "https://news.google.com/rss/articles/CBMiT0FVX3lxTFB6QmY2UkxkcXRWUVdTN29ScVMyczlDOVBpdVF6eU1nZTZCZk5wdGxjd19wTVp2OWpSTXEwZEY1ZHpnZmpJT0VpZDh1MmhfbVk?oc=5"
        }
      ]
    },
    {
      "id": "0622d62a22c9",
      "title": "脳卒中による障害が少ない側の腕を鍛えることで動作能力が向上｜医師向け医療ニュースはケアネット - CareNet.com",
      "published": "2026-03-03T19:00:00+00:00",
      "summary": "脳卒中による障害が少ない側の腕を鍛えることで動作能力が向上｜医師向け医療ニュースはケアネット&nbsp;&nbsp;CareNet.com",
      "sources": [
        {
          "name": "CareNet.com",
          "link": "https://news.google.com/rss/articles/CBMiWkFVX3lxTE52MTIxZGt0RnBrZ3ZHclBaTVZKZjZ4SmVNUkxwdWdOQ3Q0bU1UOGdkMndEeFh0WFBMdUVUM0JYU29wQjVVWlNZeGl5RFVVeTBGaDV3YjJtSWxDQQ?oc=5"
        }
      ]
    },
    {
      "id": "64cd85d7582d",
      "title": "減塩食品の普及が国民の心臓や脳を守る｜医師向け医療ニュースはケアネット - CareNet.com",
      "published": "2026-03-03T19:00:00+00:00",
      "summary": "減塩食品の普及が国民の心臓や脳を守る｜医師向け医療ニュースはケアネット&nbsp;&nbsp;CareNet.com",
      "sources": [
        {
          "name": "CareNet.com",
          "link": "https://news.google.com/rss/articles/CBMiWkFVX3lxTE9xenI5Qkp4czg4azF2dXplLWNLY25UY2ptS2h5QUR5YkJjYlZUakJ4bjh4ZHdrNmhYdXRmNmN3THYxTVJSbDJGc0k0ckdDTXo5SHFMVGcwR0VoQQ?oc=5"
        }
      ]
    },
    {
      "id": "f9aace31b985",
      "title": "うつ病予防に有効な魚の摂取量は？｜医師向け医療ニュースはケアネット - CareNet.com",
      "published": "2026-03-03T19:00:00+00:00",
      "summary": "うつ病予防に有効な魚の摂取量は？｜医師向け医療ニュースはケアネット&nbsp;&nbsp;CareNet.com",
      "sources": [
        {
          "name": "CareNet.com",
          "link": "https://news.google.com/rss/articles/CBMiX0FVX3lxTFBjbTVQVzVvSlF6SHRvYzJQdnlac1ZwWloxUVR0ZC1EZmVtQXRId05BeDBGdkx4eUlISVppY2VzeS01SXJFTW90NzRaZWUwOXZEa2wzTlc3WjJGdlUzRF9Z?oc=5"
        }
      ]
    }
  ]
}